{"name":"jsonToHTML","tagline":"node js package to covert a json object to html page ","body":"jsontoHTML\r\n==========\r\nnode js package to covert json object to html page \r\n\r\nNow you can convert a json object to html \r\n\r\n<h1>example</h1>\r\n\r\n<pre>\r\nvar test = {\r\n\thtml: {\r\n\t\thead: {\r\n\t\t\ttitle: 'test',\r\n\t\t},\r\n\t\tbody: {\r\n\t\t\th1_id_header: 'Hello World',\r\n\t\t\timg_id_logo_src:\"logo.jpg\",\r\n\t\t\th_href:[\"home.html\",home],\r\n\t\t\tul_class_menu: [{\r\n\t\t\t\t\tli: 'link1'\r\n\t\t\t\t},\r\n\t\t\t\t{\r\n\t\t\t\t\tli: 'link2 '\r\n\t\t\t\t},\r\n\t\t\t\t{\r\n\t\t\t\t\tli: ' link3'\r\n\t\t\t\t}]\r\n\t\t}\r\n\t}\r\n}\r\n\r\n</pre>\r\n<pre>\r\nvar jth = require('jsontohtml');\r\n=> jth.jsonToHTML(test,\"name\");\r\n</pre>\r\n\r\nresult =\"name.html\"\r\n<html>\r\n\t<head>\r\n\t\t<title>test</title>\r\n\t</head>\r\n\t<body>\r\n\t<h1 id=\"header\">\r\n\t\tHello world\r\n\t</h1>\r\n\t<img id='logo' src=\"logo.jpg\">\r\n\t<a href=\"home.html\">home</a>\r\n\t<ul class=\"menu\">\r\n\t\t<li>link1</li>\r\n\t\t<li>link2</li>\r\n\t\t<li>link3</li>\r\n\t</ul>\r\n\t<body>\r\n</html>\r\n\r\n","google":"","note":"Don't delete this file! It's used internally to help with page regeneration."}